odoo/addons/website_lazy_load_image/README.rst
odoo/addons/website_lazy_load_image/__init__.py
odoo/addons/website_lazy_load_image/__manifest__.py
odoo/addons/website_lazy_load_image/i18n/es.po
odoo/addons/website_lazy_load_image/i18n/website_lazy_load_image.pot
odoo/addons/website_lazy_load_image/models/__init__.py
odoo/addons/website_lazy_load_image/models/ir_ui_view.py
odoo/addons/website_lazy_load_image/readme/CONFIGURE.rst
odoo/addons/website_lazy_load_image/readme/CONTRIBUTORS.rst
odoo/addons/website_lazy_load_image/readme/CREDITS.rst
odoo/addons/website_lazy_load_image/readme/DESCRIPTION.rst
odoo/addons/website_lazy_load_image/readme/ROADMAP.rst
odoo/addons/website_lazy_load_image/readme/USAGE.rst
odoo/addons/website_lazy_load_image/static/description/icon.png
odoo/addons/website_lazy_load_image/static/description/index.html
odoo/addons/website_lazy_load_image/static/lib/jquery.lazy.js
odoo/addons/website_lazy_load_image/static/src/js/frontend.js
odoo/addons/website_lazy_load_image/templates/assets.xml
odoo/addons/website_lazy_load_image/templates/snippets.xml
odoo/addons/website_lazy_load_image/tests/__init__.py
odoo/addons/website_lazy_load_image/tests/test_lazy_load_image.py
odoo12_addon_website_lazy_load_image-12.0.1.0.1.dist-info/METADATA
odoo12_addon_website_lazy_load_image-12.0.1.0.1.dist-info/WHEEL
odoo12_addon_website_lazy_load_image-12.0.1.0.1.dist-info/top_level.txt
odoo12_addon_website_lazy_load_image-12.0.1.0.1.dist-info/RECORD
