Metadata-Version: 2.1
Name: odoo12-addon-website-lazy-load-image
Version: 12.0.1.0.1
Summary: Load images only when they are visible in the viewport.
Home-page: https://github.com/oca/website
Author: Onestein, Odoo Community Association (OCA)
Author-email: support@odoo-community.org
License: AGPL-3
Platform: UNKNOWN
Classifier: Programming Language :: Python
Classifier: Framework :: Odoo
Classifier: License :: OSI Approved :: GNU Affero General Public License v3
Requires-Python: >=3.5
Requires-Dist: odoo (<12.1dev,>=12.0a)
